metamart_schemas/__init__.py
metamart_schemas/base.py
metamart_schemas/generics.py
metamart_schemas/human_ids.py
metamart_schemas/integrations/__init__.py
metamart_schemas/integrations/base.py
metamart_schemas/integrations/errors.py
metamart_schemas/integrations/quarantine.py
metamart_schemas/package_definitions.py
metamart_schemas/py.typed
metamart_schemas/schema.py
metamart_schemas/serializers.py
metamart_schemas/utilities.py
metamart_schemas/v1/__init__.py
metamart_schemas/v1/edge.py
metamart_schemas/v1/events.py
metamart_schemas/v1/generics.py
metamart_schemas/v1/merge.py
metamart_schemas/v1/metadata/__init__.py
metamart_schemas/v1/metadata/edges.py
metamart_schemas/v1/metadata/generics.py
metamart_schemas/v1/metadata/metadata.py
metamart_schemas/v1/metadata/nodes.py
metamart_schemas/v1/mock.py
metamart_schemas/v1/node.py
metamart_schemas/v1/organization.py
metamart_schemas/v1/source.py
metamart_schemas/v1/workspace.py
metamart_schemas-0.2.11.dist-info/LICENSE
metamart_schemas-0.2.11.dist-info/METADATA
metamart_schemas-0.2.11.dist-info/WHEEL
metamart_schemas-0.2.11.dist-info/RECORD
